CHANGES.md
LICENSE.txt
MANIFEST.in
README.rst
TODO.md
pyproject.toml
setup.cfg
setup.py
tox.ini
src/g_analytics_writer/__init__.py
src/g_analytics_writer/pyramid_integration.py
src/g_analytics_writer.egg-info/PKG-INFO
src/g_analytics_writer.egg-info/SOURCES.txt
src/g_analytics_writer.egg-info/dependency_links.txt
src/g_analytics_writer.egg-info/not-zip-safe
src/g_analytics_writer.egg-info/requires.txt
src/g_analytics_writer.egg-info/top_level.txt
tests/__init__.py
tests/_utils.py
tests/test_pyramid_integration.py
tests/test_writing.py