Metadata-Version: 2.1
Name: g-analytics-writer
Version: 0.4.2
Summary: Lightweight Google Analytics support
Home-page: https://github.com/jvanasco/g_analytics_writer
Author: Jonathan Vanasco
Author-email: jonathan@findmeon.com
License: MIT
Keywords: web pyramid google analytics
Platform: UNKNOWN
Classifier: Intended Audience :: Developers
Classifier: Framework :: Pyramid
Classifier: Programming Language :: Python
Classifier: Programming Language :: Python :: 2
Classifier: Programming Language :: Python :: 3
Classifier: License :: OSI Approved :: MIT License
Provides-Extra: testing
